skyportal/__init__.py
skyportal-0.0.0.dist-info/METADATA
skyportal-0.0.0.dist-info/WHEEL
skyportal-0.0.0.dist-info/top_level.txt
skyportal-0.0.0.dist-info/RECORD
