Metadata-Version: 2.4
Name: skyportal
Version: 0.0.0
Summary: PyPi version coming soon; see GH for existing releases
Author-email: Stéfan van der Walt <stefanv@berkeley.edu>
Project-URL: Homepage, https://skyportal.io/
Project-URL: Documentation, https://skyportal.io/docs
Project-URL: Repository, https://github.com/skyportal/skyportal
Project-URL: Issues, https://github.com/skyportal/skyportal/issues
